nzsp_pms_utils/__init__.py
nzsp_pms_utils/middleware.py
nzsp_pms_utils-2.1.1.dist-info/METADATA
nzsp_pms_utils-2.1.1.dist-info/WHEEL
nzsp_pms_utils-2.1.1.dist-info/top_level.txt
nzsp_pms_utils-2.1.1.dist-info/RECORD
