Metadata-Version: 2.1
Name: nzsp-pms-utils
Version: 2.1.1
Summary: Contains code that is share across the microservices
Home-page: https://github.com/danone/nzsp.plant-management-system-utils
Author: Danone New Zealand Supply Point
Author-email: juan.parra3@danone.com
License: UNKNOWN
Platform: UNKNOWN
Classifier: Programming Language :: Python :: 3
Classifier: Topic :: Internet :: WWW/HTTP :: WSGI :: Middleware
Requires-Python: >=3.7
Requires-Dist: flask
Requires-Dist: requests
